slicematrixIO_beta/__init__.py
slicematrixIO_beta/regressors.py
slicematrixIO_beta/matrix_models.py
slicematrixIO_beta/utils.py
slicematrixIO_beta/classifiers.py
slicematrixIO_beta/graphs.py
slicematrixIO_beta/distributions.py
slicematrixIO_beta/manifolds.py
slicematrixIO_beta/connect.py
slicematrixIO_beta/notebook.py
slicematrixIO_beta/matrices.py
slicematrixIO_beta/bayesian_filters.py
slicematrixIO_beta/core.py
slicematrixIO_beta/stress_tests.py
slicematrixIO_beta/client.py
slicematrixIO_edge/__init__.py
slicematrixIO_edge/regressors.py
slicematrixIO_edge/matrix_models.py
slicematrixIO_edge/utils.py
slicematrixIO_edge/classifiers.py
slicematrixIO_edge/graphs.py
slicematrixIO_edge/distributions.py
slicematrixIO_edge/manifolds.py
slicematrixIO_edge/connect.py
slicematrixIO_edge/notebook.py
slicematrixIO_edge/matrices.py
slicematrixIO_edge/bayesian_filters.py
slicematrixIO_edge/core.py
slicematrixIO_edge/stress_tests.py
slicematrixIO_edge/client.py
slicematrixIO-beta/__init__.py
slicematrixIO-beta/regressors.py
slicematrixIO-beta/matrix_models.py
slicematrixIO-beta/utils.py
slicematrixIO-beta/classifiers.py
slicematrixIO-beta/graphs.py
slicematrixIO-beta/distributions.py
slicematrixIO-beta/manifolds.py
slicematrixIO-beta/connect.py
slicematrixIO-beta/notebook.py
slicematrixIO-beta/matrices.py
slicematrixIO-beta/bayesian_filters.py
slicematrixIO-beta/core.py
slicematrixIO-beta/stress_tests.py
slicematrixIO-beta/client.py
slicematrixIO_edge-1.0.0.dist-info/DESCRIPTION.rst
slicematrixIO_edge-1.0.0.dist-info/METADATA
slicematrixIO_edge-1.0.0.dist-info/metadata.json
slicematrixIO_edge-1.0.0.dist-info/WHEEL
slicematrixIO_edge-1.0.0.dist-info/top_level.txt
slicematrixIO_edge-1.0.0.dist-info/RECORD
