Metadata-Version: 2.0
Name: slicematrixIO-edge
Version: 1.0.0
Summary: SliceMatrix-IO Python API (Bleeding Edge)
Home-page: http://www.slicematrix.com
Author: Hekaton LLC
Author-email: tynan@slicematrix.com
License: MIT
Platform: UNKNOWN
Requires-Dist: numpy (>=1)
Requires-Dist: pandas
Requires-Dist: requests (==2.5.3)
